dojo_beam/__init__.py
dojo_beam/dataset.py
dojo_beam/storage.py
dojo_beam/transform.py
dojo_beam/util.py
dojo_beam/runners/__init__.py
dojo_beam/runners/dataflow.py
dojo_beam/runners/direct.py
dojo_beam-0.0.50.dist-info/DESCRIPTION.rst
dojo_beam-0.0.50.dist-info/METADATA
dojo_beam-0.0.50.dist-info/RECORD
dojo_beam-0.0.50.dist-info/WHEEL
dojo_beam-0.0.50.dist-info/metadata.json
dojo_beam-0.0.50.dist-info/top_level.txt
