Metadata-Version: 2.0
Name: dojo-beam
Version: 0.0.50
Summary: Apache Beam adapters and datasets for the Dojo data framework.
Home-page: https://dojo.dataup.io/
Author: Steven Normore
Author-email: steven@dataup.io
License: UNKNOWN
Platform: UNKNOWN
Requires-Dist: dojo
Requires-Dist: apache-beam[gcp]
